ciomaya/VERSION
ciomaya/__init__.py
ciomaya/post_install.py
ciomaya/icons/ConductorConnect_18x18.png
ciomaya/icons/ConductorConnect_24x24.png
ciomaya/icons/ConductorConnect_30x30.png
ciomaya/icons/ConductorConnect_36x36.png
ciomaya/icons/ConductorError_18x18.png
ciomaya/icons/ConductorError_24x24.png
ciomaya/icons/ConductorError_30x30.png
ciomaya/icons/ConductorError_36x36.png
ciomaya/icons/ConductorHelp_18x18.png
ciomaya/icons/ConductorHelp_24x24.png
ciomaya/icons/ConductorHelp_30x30.png
ciomaya/icons/ConductorHelp_36x36.png
ciomaya/icons/ConductorInfo_18x18.png
ciomaya/icons/ConductorInfo_24x24.png
ciomaya/icons/ConductorInfo_30x30.png
ciomaya/icons/ConductorInfo_36x36.png
ciomaya/icons/ConductorReload_18x18.png
ciomaya/icons/ConductorReload_24x24.png
ciomaya/icons/ConductorReload_30x30.png
ciomaya/icons/ConductorReload_36x36.png
ciomaya/icons/ConductorSend_18x18.png
ciomaya/icons/ConductorSend_24x24.png
ciomaya/icons/ConductorSend_30x30.png
ciomaya/icons/ConductorSend_36x36.png
ciomaya/icons/ConductorShow_18x18.png
ciomaya/icons/ConductorShow_24x24.png
ciomaya/icons/ConductorShow_30x30.png
ciomaya/icons/ConductorShow_36x36.png
ciomaya/icons/ConductorSubmit_18x18.png
ciomaya/icons/ConductorSubmit_24x24.png
ciomaya/icons/ConductorSubmit_30x30.png
ciomaya/icons/ConductorSubmit_36x36.png
ciomaya/icons/ConductorValidate_18x18.png
ciomaya/icons/ConductorValidate_24x24.png
ciomaya/icons/ConductorValidate_30x30.png
ciomaya/icons/ConductorValidate_36x36.png
ciomaya/icons/ConductorWarning_18x18.png
ciomaya/icons/ConductorWarning_24x24.png
ciomaya/icons/ConductorWarning_30x30.png
ciomaya/icons/ConductorWarning_36x36.png
ciomaya/icons/banner.png
ciomaya/icons/banner_sm.png
ciomaya/icons/conductorRender.png
ciomaya/icons/conductor_logo_white.png
ciomaya/icons/out_conductorRender.png
ciomaya/lib/__init__.py
ciomaya/lib/about_window.py
ciomaya/lib/asset_cache.py
ciomaya/lib/conductor_menu.py
ciomaya/lib/const.py
ciomaya/lib/context.py
ciomaya/lib/layer_utils.py
ciomaya-1.1.0.dist-info/METADATA
ciomaya-1.1.0.dist-info/WHEEL
ciomaya-1.1.0.dist-info/top_level.txt
ciomaya-1.1.0.dist-info/RECORD
