Metadata-Version: 2.1
Name: ciomaya
Version: 1.1.0
Summary: Maya plugin for Conductor Cloud Rendering Platform.
Home-page: https://github.com/ConductorTechnologies/ciomaya
Author: conductor
Author-email: info@conductortech.com
Classifier: Operating System :: OS Independent
Classifier: Programming Language :: Python
Classifier: Topic :: Multimedia :: Graphics :: 3D Rendering
Requires-Dist: ciocore<10.0.0,>=9.1.0
Requires-Dist: pymel<2.0.0,>=1.5.0
Requires-Dist: ciopath<2.0.0,>=1.1.2
Requires-Dist: cioseq<1.0.0,>=0.5.1
Requires-Dist: ciotemplate<1.0.0,>=0.1.2
